debt_optimization/__init__.py
debt_optimization/architecture/__init__.py
debt_optimization/architecture/neural_architecture.py
debt_optimization/core/__init__.py
debt_optimization/core/debt_core.py
debt_optimization/core/evaluation_modes.py
debt_optimization/evaluation/__init__.py
debt_optimization/evaluation/adapter.py
debt_optimization/evaluation/real_training.py
debt_optimization/evaluation/surrogate.py
debt_optimization/optimizer/__init__.py
debt_optimization/optimizer/optimizer.py
debt_optimization/utils/__init__.py
debt_optimization/utils/visualization.py
debt_optimization-1.0.1.dist-info/licenses/LICENSE
examples/__init__.py
examples/demo.py
examples/simple_usage.py
debt_optimization-1.0.1.dist-info/METADATA
debt_optimization-1.0.1.dist-info/WHEEL
debt_optimization-1.0.1.dist-info/top_level.txt
debt_optimization-1.0.1.dist-info/RECORD
